TiRiFiG/TiRiFiG_launcher.py
TiRiFiG/__init__.py
TiRiFiG/utilities/example/n5204_lo_out_00.def
TiRiFiG/utilities/icons/edit.png
TiRiFiG/utilities/icons/open_folder.png
TiRiFiG/utilities/icons/plus.png
TiRiFiG-1.0.1.dist-info/METADATA
TiRiFiG-1.0.1.dist-info/RECORD
TiRiFiG-1.0.1.dist-info/WHEEL
TiRiFiG-1.0.1.dist-info/entry_points.txt
TiRiFiG-1.0.1.dist-info/top_level.txt
