Metadata-Version: 2.1
Name: TiRiFiG
Version: 1.0.1
Summary: A graphical user interface that allows users of TiRiFiC to modify tilted-ring parameters interactively.
Home-page: https://github.com/gigjozsa/samtirifik
Author: Samuel Twum
Author-email: samueltwum1@gmail.com
License: MIT
Download-URL: https://pypi.python.org/pypi/samtirifik
Platform: OS Independent
Classifier: Development Status :: 4 - Beta
Classifier: Intended Audience :: Science/Research
Classifier: License :: OSI Approved :: MIT License
Classifier: Operating System :: OS Independent
Classifier: Programming Language :: Python :: 2
Classifier: Topic :: Scientific/Engineering :: Visualization
Requires-Dist: numpy
Requires-Dist: matplotlib
